fedora_sig_onboard/__init__.py
fedora_sig_onboard/cli.py
fedora_sig_onboard/onboarder.py
fedora_sig_onboard-0.1.1.dist-info/LICENSE
fedora_sig_onboard-0.1.1.dist-info/METADATA
fedora_sig_onboard-0.1.1.dist-info/WHEEL
fedora_sig_onboard-0.1.1.dist-info/entry_points.txt
fedora_sig_onboard-0.1.1.dist-info/top_level.txt
fedora_sig_onboard-0.1.1.dist-info/RECORD
