Metadata-Version: 2.1
Name: fedora-sig-onboard
Version: 0.1.1
Summary: Onboard a package onto the appropriate Fedora SIG
Author: Davide Cavalca
Author-email: dcavalca@fedoraproject.org
License: MIT
Classifier: Development Status :: 2 - Pre-Alpha
Classifier: Environment :: Console
Classifier: Intended Audience :: Developers
Classifier: License :: OSI Approved :: MIT License
Requires-Python: >=3.9
License-File: LICENSE
Requires-Dist: click
Requires-Dist: pyxdg
Requires-Dist: requests
